mlpype/mlflow/__init__.py
mlpype/mlflow/deploy/__init__.py
mlpype/mlflow/deploy/load_experiment.py
mlpype/mlflow/logger/__init__.py
mlpype/mlflow/logger/mlflow_logger.py
mlpype/mlflow/model/__init__.py
mlpype/mlflow/model/model.py
mlpype_mlflow-0.6.12.dist-info/METADATA
mlpype_mlflow-0.6.12.dist-info/WHEEL
mlpype_mlflow-0.6.12.dist-info/RECORD
