Metadata-Version: 2.4
Name: mlpype-mlflow
Version: 0.6.12
Summary: MLflow extension for MLpype
Author: Jeroen van den Hoven
License: MIT
Requires-Python: >=3.9
Requires-Dist: gitpython>=3.1.27
Requires-Dist: mlflow>=2.17.0
Requires-Dist: mlpype-base
Provides-Extra: strict
Requires-Dist: gitpython==3.1.27; extra == 'strict'
Requires-Dist: mlflow==2.17.0; extra == 'strict'
